JoTools/__init__.py
JoTools/txkjRes/__init__.py
JoTools/txkjRes/deteAngleObj.py
JoTools/txkjRes/deteObj.py
JoTools/txkjRes/deteRes.py
JoTools/txkjRes/deteXml.py
JoTools/txkjRes/resBase.py
JoTools/txkjRes/resTools.py
JoTools/utils/FileOperationUtil.py
JoTools/utils/JsonUtil.py
JoTools/utils/XmlUtil.py
JoTools/utils/__init__.py
JoUtilCM-0.0.1.dist-info/METADATA
JoUtilCM-0.0.1.dist-info/WHEEL
JoUtilCM-0.0.1.dist-info/top_level.txt
JoUtilCM-0.0.1.dist-info/RECORD
