Metadata-Version: 2.1
Name: JoUtilCM
Version: 0.0.1
Summary: a tools for TXKJ algo
Home-page: UNKNOWN
Author: jokker
Author-email: 18761609908@163.com
License: UNKNOWN
Platform: UNKNOWN
Requires: numpy
Requires: pillow
Requires: pandas
Requires: easydict
Requires: matplotlib
Requires: imagehash
Requires: prettytable
Requires: progress
Requires: progressbar
Requires: requests
Requires: imageio
Requires: pyexiv2
Requires: cv2
Requires: exifread
Requires: whatimage
Requires: pyheif
Requires: pymysql
Requires: pytesseract
Requires: beautifulsoup4
Requires: Crypto
Requires: flask
